iloadmagics/__init__.py
iloadmagics/_version.py
iloadmagics/iloadmagics.py
iloadmagics-0.1.0.data/data/share/jupyter/labextensions/iloadmagics/build_log.json
iloadmagics-0.1.0.data/data/share/jupyter/labextensions/iloadmagics/package.json
iloadmagics-0.1.0.data/data/share/jupyter/labextensions/iloadmagics/static/lib_index_js.14ef966552e82335a53e.js
iloadmagics-0.1.0.data/data/share/jupyter/labextensions/iloadmagics/static/lib_index_js.14ef966552e82335a53e.js.map
iloadmagics-0.1.0.data/data/share/jupyter/labextensions/iloadmagics/static/remoteEntry.b2f321db59888c552eef.js
iloadmagics-0.1.0.data/data/share/jupyter/labextensions/iloadmagics/static/remoteEntry.b2f321db59888c552eef.js.map
iloadmagics-0.1.0.data/data/share/jupyter/labextensions/iloadmagics/static/style.js
iloadmagics-0.1.0.data/data/share/jupyter/labextensions/iloadmagics/static/style_index_js.cbb38d857f7eea2f9446.js
iloadmagics-0.1.0.data/data/share/jupyter/labextensions/iloadmagics/static/style_index_js.cbb38d857f7eea2f9446.js.map
iloadmagics-0.1.0.data/data/share/jupyter/labextensions/iloadmagics/install.json
iloadmagics-0.1.0.dist-info/METADATA
iloadmagics-0.1.0.dist-info/WHEEL
iloadmagics-0.1.0.dist-info/licenses/LICENSE
iloadmagics-0.1.0.dist-info/RECORD
